natml/__init__.py
natml/version.py
natml/api/__init__.py
natml/api/api.py
natml/api/dtype.py
natml/api/endpoint.py
natml/api/feature.py
natml/api/graph.py
natml/api/license.py
natml/api/predictor.py
natml/api/profile.py
natml/api/storage.py
natml/api/tag.py
natml/api/user.py
natml/api/prediction/__init__.py
natml/api/prediction/endpoint.py
natml/api/prediction/feature.py
natml/api/prediction/graph.py
natml/cli/__init__.py
natml/cli/auth.py
natml/cli/demos.py
natml/cli/endpoints.py
natml/cli/graphs.py
natml/cli/misc.py
natml/cli/predict.py
natml/cli/predictors.py
natml/cli/users.py
natml-0.0.14.dist-info/LICENSE
natml-0.0.14.dist-info/METADATA
natml-0.0.14.dist-info/WHEEL
natml-0.0.14.dist-info/entry_points.txt
natml-0.0.14.dist-info/top_level.txt
natml-0.0.14.dist-info/RECORD
