Metadata-Version: 2.1
Name: natml
Version: 0.0.14
Summary: Zero deployment machine learning.
Home-page: https://natml.ai
Author: NatML Inc.
Author-email: hi@natml.ai
License: Apache License 2.0
Project-URL: Documentation, https://docs.natml.ai/python
Project-URL: Source, https://github.com/natmlx/natml-py
Platform: UNKNOWN
Classifier: Programming Language :: Python :: 3
Classifier: License :: OSI Approved :: Apache Software License
Classifier: Operating System :: OS Independent
Classifier: Topic :: Scientific/Engineering :: Image Recognition
Classifier: Topic :: Software Development :: Libraries
Requires-Python: >=3.7
Requires-Dist: filetype
Requires-Dist: numpy
Requires-Dist: pillow
Requires-Dist: requests
Requires-Dist: rich
Requires-Dist: typer
